pycograph/__init__.py
pycograph/ast_to_basic_syntax_elements.py
pycograph/cli.py
pycograph/config.py
pycograph/exceptions.py
pycograph/helpers/__init__.py
pycograph/helpers/name_analyzer.py
pycograph/parse_result_to_redisgraph.py
pycograph/project.py
pycograph/pycograph.py
pycograph/schemas/__init__.py
pycograph/schemas/basic_syntax_elements.py
pycograph/schemas/parse_result.py
pycograph/schemas/pycograph_input.py
pycograph-0.3.0.dist-info/entry_points.txt
pycograph-0.3.0.dist-info/LICENSE
pycograph-0.3.0.dist-info/WHEEL
pycograph-0.3.0.dist-info/METADATA
pycograph-0.3.0.dist-info/RECORD
